connexity_pipecat/__init__.py
connexity_pipecat/api/__init__.py
connexity_pipecat/api/handlers.py
connexity_pipecat/api/router.py
connexity_pipecat/core/__init__.py
connexity_pipecat/core/config.py
connexity_pipecat/core/prompts.py
connexity_pipecat/core/tools.py
connexity_pipecat/core/generators/__init__.py
connexity_pipecat/core/generators/management.py
connexity_pipecat/core/generators/functions/current_timestamp.py
connexity_pipecat/core/generators/functions/get_available_time_slots.py
connexity_pipecat/core/generators/functions/get_grouped_calendar.py
connexity_pipecat/core/voice_calls/__init__.py
connexity_pipecat/core/voice_calls/templates.py
connexity_pipecat/core/voice_calls/twilio_service.py
connexity_pipecat/core/voice_calls/helpers/EndCallProcessor.py
connexity_pipecat/core/voice_calls/helpers/__init__.py
connexity_pipecat/core/voice_calls/helpers/end_call.py
connexity_pipecat/core/voice_calls/helpers/get_tts_service.py
connexity_pipecat/core/voice_calls/helpers/initiate_vad_params.py
connexity_pipecat/data/__init__.py
connexity_pipecat/data/consts.py
connexity_pipecat/data/schemas.py
connexity_pipecat/data/validators.py
connexity_pipecat/helpers/__init__.py
connexity_pipecat/helpers/append_message_history_to_function.py
connexity_pipecat/helpers/get_model.py
connexity_pipecat/helpers/make_openai_call.py
connexity_pipecat/helpers/message_history_to_plain_text.py
connexity_pipecat/helpers/perform_post_call_analytics.py
connexity_pipecat/helpers/with_agent_id.py
connexity_pipecat-0.1.38.dist-info/licenses/LICENSE
connexity_pipecat-0.1.38.dist-info/METADATA
connexity_pipecat-0.1.38.dist-info/WHEEL
connexity_pipecat-0.1.38.dist-info/top_level.txt
connexity_pipecat-0.1.38.dist-info/RECORD
