Metadata-Version: 2.4
Name: connexity_pipecat
Version: 0.1.38
Summary: AI outbound voice agent framework
Author-email: Max Ilin <maksym@spacestep.ca>
License-Expression: MIT
Requires-Python: >=3.9
License-File: LICENSE
Requires-Dist: aiohttp==3.11.16
Requires-Dist: annotated-types==0.7.0
Requires-Dist: anyio==4.8.0
Requires-Dist: cachetools==5.3.3
Requires-Dist: certifi==2025.1.31
Requires-Dist: click==8.1.8
Requires-Dist: colorama==0.4.6
Requires-Dist: connexity==0.0.8.9
Requires-Dist: distro==1.9.0
Requires-Dist: dnspython==2.7.0
Requires-Dist: email_validator==2.2.0
Requires-Dist: fastapi>=0.115.12
Requires-Dist: fastapi-cli==0.0.7
Requires-Dist: fireworks-ai==0.15.12
Requires-Dist: google-cloud-aiplatform>=1.38
Requires-Dist: groq==0.9.0
Requires-Dist: h11==0.14.0
Requires-Dist: httpcore==1.0.7
Requires-Dist: httptools==0.6.4
Requires-Dist: httpx==0.28.1
Requires-Dist: httpx-sse==0.4.0
Requires-Dist: httpx-ws==0.7.1
Requires-Dist: idna==3.10
Requires-Dist: Jinja2==3.1.5
Requires-Dist: loguru==0.7.3
Requires-Dist: markdown-it-py==3.0.0
Requires-Dist: MarkupSafe==3.0.2
Requires-Dist: mdurl==0.1.2
Requires-Dist: noisereduce==3.0.3
Requires-Dist: openai==1.70.0
Requires-Dist: orjson==3.10.15
Requires-Dist: pipecat-ai[cartesia,deepgram,google,lmnt,openai,rime,silero]==0.0.73
Requires-Dist: pillow==11.1.0
Requires-Dist: pydantic==2.10.6
Requires-Dist: pydantic_core==2.27.2
Requires-Dist: pydub==0.25.1
Requires-Dist: pyht==0.1.14
Requires-Dist: python-multipart==0.0.20
Requires-Dist: PyYAML==6.0.2
Requires-Dist: Pygments==2.19.1
Requires-Dist: requests~=2.32.3
Requires-Dist: rich==13.9.4
Requires-Dist: rich-toolkit==0.13.2
Requires-Dist: spacestep-tools==0.1.4
Requires-Dist: shellingham==1.5.4
Requires-Dist: sniffio==1.3.1
Requires-Dist: soundfile==0.13.1
Requires-Dist: starlette>=0.37.2
Requires-Dist: tqdm==4.67.1
Requires-Dist: twilio==9.6.0
Requires-Dist: typer==0.15.1
Requires-Dist: typing_extensions==4.12.2
Requires-Dist: ujson==5.10.0
Requires-Dist: uvicorn==0.32.1
Requires-Dist: watchfiles==1.0.4
Requires-Dist: websockets==13.1
Requires-Dist: wsproto==1.2.0
Provides-Extra: dev
Requires-Dist: pytest; extra == "dev"
Requires-Dist: ruff; extra == "dev"
Requires-Dist: black; extra == "dev"
Requires-Dist: pre-commit; extra == "dev"
Provides-Extra: docs
Requires-Dist: mkdocs; extra == "docs"
Requires-Dist: mkdocstrings; extra == "docs"
Dynamic: license-file
